zerolan/data/__init__.py
zerolan/data/data/danmaku.py
zerolan/data/data/prompt.py
zerolan/data/data/state.py
zerolan/data/pipeline/abs_data.py
zerolan/data/pipeline/asr.py
zerolan/data/pipeline/img_cap.py
zerolan/data/pipeline/llm.py
zerolan/data/pipeline/ocr.py
zerolan/data/pipeline/tts.py
zerolan/data/pipeline/vid_cap.py
zerolan_data-1.0.0.dist-info/METADATA
zerolan_data-1.0.0.dist-info/WHEEL
zerolan_data-1.0.0.dist-info/RECORD
